azure/ai/evaluation/__init__.py
azure/ai/evaluation/_constants.py
azure/ai/evaluation/_eval_mapping.py
azure/ai/evaluation/_evaluator_definition.py
azure/ai/evaluation/_exceptions.py
azure/ai/evaluation/_http_utils.py
azure/ai/evaluation/_model_configurations.py
azure/ai/evaluation/_user_agent.py
azure/ai/evaluation/_version.py
azure/ai/evaluation/py.typed
azure/ai/evaluation/_aoai/__init__.py
azure/ai/evaluation/_aoai/aoai_grader.py
azure/ai/evaluation/_aoai/label_grader.py
azure/ai/evaluation/_aoai/python_grader.py
azure/ai/evaluation/_aoai/score_model_grader.py
azure/ai/evaluation/_aoai/string_check_grader.py
azure/ai/evaluation/_aoai/text_similarity_grader.py
azure/ai/evaluation/_azure/__init__.py
azure/ai/evaluation/_azure/_clients.py
azure/ai/evaluation/_azure/_envs.py
azure/ai/evaluation/_azure/_models.py
azure/ai/evaluation/_azure/_token_manager.py
azure/ai/evaluation/_common/__init__.py
azure/ai/evaluation/_common/_experimental.py
azure/ai/evaluation/_common/constants.py
azure/ai/evaluation/_common/evaluation_onedp_client.py
azure/ai/evaluation/_common/math.py
azure/ai/evaluation/_common/rai_service.py
azure/ai/evaluation/_common/utils.py
azure/ai/evaluation/_common/onedp/__init__.py
azure/ai/evaluation/_common/onedp/_client.py
azure/ai/evaluation/_common/onedp/_configuration.py
azure/ai/evaluation/_common/onedp/_model_base.py
azure/ai/evaluation/_common/onedp/_patch.py
azure/ai/evaluation/_common/onedp/_serialization.py
azure/ai/evaluation/_common/onedp/_types.py
azure/ai/evaluation/_common/onedp/_validation.py
azure/ai/evaluation/_common/onedp/_vendor.py
azure/ai/evaluation/_common/onedp/_version.py
azure/ai/evaluation/_common/onedp/py.typed
azure/ai/evaluation/_common/onedp/_utils/__init__.py
azure/ai/evaluation/_common/onedp/_utils/model_base.py
azure/ai/evaluation/_common/onedp/_utils/serialization.py
azure/ai/evaluation/_common/onedp/aio/__init__.py
azure/ai/evaluation/_common/onedp/aio/_client.py
azure_ai_evaluation-1.13.7.dist-info/licenses/NOTICE.txt
azure_ai_evaluation-1.13.7.dist-info/METADATA
azure_ai_evaluation-1.13.7.dist-info/WHEEL
azure_ai_evaluation-1.13.7.dist-info/top_level.txt
azure_ai_evaluation-1.13.7.dist-info/RECORD
