Metadata-Version: 2.4
Name: azure-ai-evaluation
Version: 1.13.7
Summary: Microsoft Azure Evaluation Library for Python
Home-page: https://github.com/Azure/azure-sdk-for-python
Author: Microsoft Corporation
Author-email: azuresdkengsysadmins@microsoft.com
License: MIT License
Project-URL: Bug Reports, https://github.com/Azure/azure-sdk-for-python/issues
Project-URL: Source, https://github.com/Azure/azure-sdk-for-python
Keywords: azure,azure sdk
Classifier: Development Status :: 5 - Production/Stable
Classifier: Programming Language :: Python
Classifier: Programming Language :: Python :: 3
Classifier: Programming Language :: Python :: 3 :: Only
Classifier: Programming Language :: Python :: 3.9
Classifier: Programming Language :: Python :: 3.10
Classifier: Programming Language :: Python :: 3.11
Classifier: License :: OSI Approved :: MIT License
Classifier: Operating System :: OS Independent
Requires-Python: >=3.9
License-File: NOTICE.txt
Requires-Dist: pyjwt>=2.8.0
Requires-Dist: azure-identity>=1.19.0
Requires-Dist: azure-core>=1.31.0
Requires-Dist: nltk>=3.9.1
Requires-Dist: azure-storage-blob>=12.19.0
Requires-Dist: httpx>=0.27.2
Requires-Dist: pandas<3.0.0,>=2.1.2; python_version < "3.13"
Requires-Dist: pandas<3.0.0,>=2.2.3; python_version == "3.13"
Requires-Dist: pandas<3.0.0,>=2.3.3; python_version >= "3.14"
Requires-Dist: openai>=1.108.0
Requires-Dist: ruamel.yaml<1.0.0,>=0.17.10
Requires-Dist: msrest>=0.6.21
Requires-Dist: Jinja2>=3.1.6
Requires-Dist: aiohttp>=3.0
Provides-Extra: redteam
Requires-Dist: pyrit==0.8.1; python_version >= "3.10" and extra == "redteam"
Requires-Dist: duckdb==1.3.2; python_version >= "3.10" and extra == "redteam"
Provides-Extra: opentelemetry
Requires-Dist: opentelemetry-sdk>=1.17.0; extra == "opentelemetry"
Requires-Dist: azure-monitor-opentelemetry-exporter>=1.0.0b17; extra == "opentelemetry"
Dynamic: author
Dynamic: author-email
Dynamic: classifier
Dynamic: description
Dynamic: description-content-type
Dynamic: home-page
Dynamic: keywords
Dynamic: license
Dynamic: license-file
Dynamic: project-url
Dynamic: provides-extra
Dynamic: requires-dist
Dynamic: requires-python
Dynamic: summary
